media_hoard_cli/__init__.py
media_hoard_cli/cli.py
media_hoard_cli/hoard.py
media_hoard_cli/media_hoard_cli.py
media_hoard_cli/templates/pdf_parts.ods
media_hoard_cli-0.2.2.dist-info/entry_points.txt
media_hoard_cli-0.2.2.dist-info/LICENSE
media_hoard_cli-0.2.2.dist-info/WHEEL
media_hoard_cli-0.2.2.dist-info/METADATA
media_hoard_cli-0.2.2.dist-info/RECORD
