Metadata-Version: 2.1
Name: media-hoard-cli
Version: 0.2.2
Summary: Top-level package for Media Hoard CLI.
Home-page: https://github.com/midwatch/media_hoard_cli
License: MIT
Author: Justin Stout
Author-email: midwatch@jstout.us
Requires-Python: >=3.8,<4.0
Classifier: Development Status :: 2 - Pre-Alpha
Classifier: Intended Audience :: Developers
Classifier: License :: OSI Approved :: MIT License
Classifier: Natural Language :: English
Classifier: Programming Language :: Python :: 3
Classifier: Programming Language :: Python :: 3.10
Classifier: Programming Language :: Python :: 3.8
Classifier: Programming Language :: Python :: 3.9
Requires-Dist: PyPDF4 (>=1.27.0,<2.0.0)
Requires-Dist: PyYAML (>=6.0,<7.0)
Requires-Dist: click
Requires-Dist: nanoid (>=2.0.0,<3.0.0)
